vbelt/__init__.py
vbelt/charge_utils.py
vbelt/chargetool.py
vbelt/coherence.py
vbelt/forces.py
vbelt/gencalc.py
vbelt/incar.py
vbelt/jobtool.py
vbelt/kpoints.py
vbelt/logger.py
vbelt/misc.py
vbelt/outcar.py
vbelt/outcar_utils.py
vbelt/poscar.py
vbelt/poscartool.py
vbelt/potcar.py
vbelt/script_utils.py
vbelt/wrapper.py
vbelt-0.8.2.dist-info/METADATA
vbelt-0.8.2.dist-info/WHEEL
vbelt-0.8.2.dist-info/entry_points.txt
vbelt-0.8.2.dist-info/licenses/LICENSE
vbelt-0.8.2.dist-info/RECORD
