Metadata-Version: 2.3
Name: vbelt
Version: 0.8.2
Summary: The VASP user's tool belt.
Project-URL: Homepage, https://git.sr.ht/~lattay/vbelt
Author-email: Théo Cavignac <theo.cavignac@gmail.com>
License: EUPL-1.2
Classifier: Environment :: Console
Classifier: Programming Language :: Python :: 3.7
Requires-Dist: numpy>=1.16
Provides-Extra: gencalc
Requires-Dist: ase>=3.22; extra == 'gencalc'
Requires-Dist: chevron>=0.14.0; extra == 'gencalc'
Requires-Dist: tc-pysh>=0.2.0; extra == 'gencalc'
Provides-Extra: symmetry
Requires-Dist: pymatgen; extra == 'symmetry'
